Workbook

Sheet Assumptions
A1: Scenario 1: Sell As-Is — Assumptions
A2: 648 & 650 Grassmere Park Drive, Nashville, TN 37211
A3: Blue = adjustable inputs | Black = formulas | Source notes in Column E
A5: SUBJECT PROPERTY
A6: Total Building Area (SF) | B6: 224199 | C6: Building Area | E6: Source: Exhibit A, Case Study
A7: Main Building (SF) | B7: 162550 | C7: Annex Building (SF) | D7: 61649 | E7: Source: Exhibit A
A8: Total Site Area (acres) | B8: 23.49 | C8: Total Site Area (SF) | D8: =B8*43560 -> 1023224.4 | E8: Source: Exhibit A
A9: Year Built | B9: 1985 | C9: Building Age (2026) | D9: =2026-B9 -> 41
A10: Zoning | B10: IWD | C10: Parking Spaces | D10: 1205
A11: Current Appraised Value | B11: 37400600 | C11: Appraised $/SF | D11: =B11/B6 -> 166.81876 | E11: Source: Davidson Co. Assessor
A12: Acquisition Price (2015) | B12: 25938000 | C12: Acquisition $/SF | D12: =B12/B6 -> 115.69186 | E12: Source: Exhibit E, Ownership History
A14: CAPITAL STRUCTURE (Exhibit G)
A15: Loan Balance | B15: 16252413 | C15: Loan Effective Date | D15: 11/5/2024 | E15: Source: Exhibit G
A16: SOFR Rate (at closing) | B16: 0.0443 | C16: Spread (bps) | D16: 450 | E16: Source: Exhibit G
A17: All-In Interest Rate | B17: =B16+D16/10000 -> 0.0893 | C17: Day Count | D17: 30/360
A18: Annual Debt Service (IO) | B18: =B15*B17 -> 1451340.5 | C18: Loan Maturity | D18: December 2029 | E18: Source: Exhibit G
A19: Monthly Debt Service | B19: =B18/12 -> 120945.04 | C19: Interest Only Period | D19: 60 months
A21: CURRENT OPERATING INCOME (Exhibit F)
A22: Asurion Annual Rent | B22: 1047633 | C22: Asurion Lease Expiration | D22: March 2027 | E22: Source: Exhibit F / Case Study
A23: Other Rental Income | B23: 401932 | C23: Tenant Reimbursements | D23: 208428 | E23: Source: Exhibit F
A24: Total Revenue (2025 Budget) | B24: =B22+B23+D23 -> 1657993 | C24: Occupancy Rate (Annex) | D24: 27% | E24: Source: Exhibit F (61,649 / 224,199)
A25: Total Operating Expenses | B25: 1122726 | C25: Management Fee | D25: 44292 | E25: Source: Exhibit F
A26: Net Operating Income (NOI) | B26: =B24-B25-D25 -> 490975 | C26: Interest Expense (2025) | D26: 1409165 | E26: Source: Exhibit F
A28: SCENARIO 1: SALE ASSUMPTIONS
A29: Low Sale Price ($/SF) | B29: 65 | C29: Low Total Sale Price | D29: =B29*B6 -> 14572935 | E29: Comp-supported: distressed suburban office
A30: Base Sale Price ($/SF) | B30: 85 | C30: Base Total Sale Price | D30: =B30*B6 -> 19056915 | E30: Comp-supported: 424 Church, Burton Hills
A31: High Sale Price ($/SF) | B31: 115 | C31: High Total Sale Price | D31: =B31*B6 -> 25782885 | E31: Near acquisition basis ($116/SF)
A32: Selling Costs (% of sale) | B32: 0.02 | E32: Broker commissions + legal
A33: Marketing Period (months) | B33: 6 | C33: Monthly Carry Cost | D33: =B19 -> 120945.04 | E33: Debt service during marketing
A34: Buyer Cap Rate (Asurion) | B34: 0.085 | C34: Income Approach Value | D34: =B22/B34 -> 12325094 | E34: Applied to Asurion NOI only

Sheet Sell As-Is
A1: Scenario 1: Sell Property As-Is
A2: 648 & 650 Grassmere Park Drive, Nashville, TN 37211
B4: Low Case | C4: Base Case | D4: High Case
A5: SALE PROCEEDS
A6: Sale Price ($/SF) | B6: =Assumptions!B29 -> 65 | C6: =Assumptions!B30 -> 85 | D6: =Assumptions!B31 -> 115
A7: Gross Sale Price | B7: =B6*Assumptions!B6 -> 14572935 | C7: =C6*Assumptions!B6 -> 19056915 | D7: =D6*Assumptions!B6 -> 25782885
A8: Less: Selling Costs | B8: =-B7*Assumptions!B32 -> -291458.7 | C8: =-C7*Assumptions!B32 -> -381138.3 | D8: =-D7*Assumptions!B32 -> -515657.7 | E8: 2% of gross sale price
A9: Less: Carry Cost (marketing period) | B9: =-Assumptions!B19*Assumptions!B33 -> -725670.24 | C9: =B9 -> -725670.24 | D9: =B9 -> -725670.24 | E9: 6 months debt service during marketing
A10: Net Sale Proceeds | B10: =SUM(B7:B9) -> 13555806 | C10: =SUM(C7:C9) -> 17950106 | D10: =SUM(D7:D9) -> 24541557
A12: DEBT RETIREMENT
A13: Existing Loan Balance | B13: =Assumptions!B15 -> 16252413 | C13: =B13 -> 16252413 | D13: =B13 -> 16252413 | E13: Source: Exhibit G, $16.25M IO loan
A14: Net Proceeds Less Debt | B14: =B10-B13 -> -2696606.9 | C14: =C10-C13 -> 1697693.5 | D14: =D10-D13 -> 8289144.1
A15: Surplus / (Shortfall) | B15: =IF(B14>=0,"SURPLUS","SHORTFALL") -> SHORTFALL | C15: =IF(C14>=0,"SURPLUS","SHORTFALL") -> SURPLUS | D15: =IF(D14>=0,"SURPLUS","SHORTFALL") -> SURPLUS
A17: INCOME APPROACH VALUATION
A18: Asurion Annual Rent (in-place) | B18: =Assumptions!B22 -> 1047633
A19: Less: Estimated OpEx (annex) | B19: =-Assumptions!B22*0.35 -> -366671.55 | E19: Est. 35% expense ratio on annex
A20: Annex NOI | B20: =B18+B19 -> 680961.45
A21: Buyer Cap Rate | B21: =Assumptions!B34 -> 0.085
A22: Implied Value (Income Approach) | B22: =IF(B21>0,B20/B21,0) -> 8011311.2 | E22: Annex NOI / Cap Rate — occupied portion only
A23: Income Approach $/SF (on total bldg) | B23: =B22/Assumptions!B6 -> 35.733037
A25: EQUITY POSITION ANALYSIS
A26: Original Equity (Acq. Price - Loan) | B26: =Assumptions!B12-Assumptions!B15 -> 9685587 | E26: $25.9M acquisition - $16.3M loan
A27: Cumulative Cash Shortfalls (est.) | B27: 5000000 | E27: Est. negative cash flow since 2022 vacancy
A28: Total Equity at Risk | B28: =B26+B27 -> 14685587
A29: Equity Recovered (Net Proceeds - Debt) | B29: =C14 -> 1697693.5 | E29: Base case net proceeds after debt payoff
A30: Net Equity Loss | B30: =B28-IF(B29>0,B29,0) -> 12987894
A32: SUBJECT PROPERTY DISCOUNT FACTORS
A33: 73% vacant — main building empty since 2022
A34: Asurion annex lease expires March 2027 (no renewal expected)
A35: Single access point (Trousdale Drive only)
A36: CC&Rs restrict uses until February 2033
A37: Loan maturity December 2029 creates time pressure
A38: IWD zoning limits buyer pool to industrial/warehouse users
A39: 41-year-old building requires significant capital investment

Sheet Sensitivity Analysis
A1: Sensitivity: Sale Price vs. Net Equity Position
A3: Sale Price ($/SF) | B3: Gross Proceeds | C3: Net Proceeds | D3: Less Debt | E3: Surplus / (Shortfall)
A4: 50 | B4: =A4*Assumptions!B6 -> 11209950 | C4: =B4*(1-Assumptions!B32)-Assumptions!B19*Assumptions!B33 -> 10260081 | D4: =-Assumptions!B15 -> -16252413 | E4: =C4+D4 -> -5992332.2
A5: 60 | B5: =A5*Assumptions!B6 -> 13451940 | C5: =B5*(1-Assumptions!B32)-Assumptions!B19*Assumptions!B33 -> 12457231 | D5: =-Assumptions!B15 -> -16252413 | E5: =C5+D5 -> -3795182
A6: 65 | B6: =A6*Assumptions!B6 -> 14572935 | C6: =B6*(1-Assumptions!B32)-Assumptions!B19*Assumptions!B33 -> 13555806 | D6: =-Assumptions!B15 -> -16252413 | E6: =C6+D6 -> -2696606.9
A7: 70 | B7: =A7*Assumptions!B6 -> 15693930 | C7: =B7*(1-Assumptions!B32)-Assumptions!B19*Assumptions!B33 -> 14654381 | D7: =-Assumptions!B15 -> -16252413 | E7: =C7+D7 -> -1598031.8
A8: 75 | B8: =A8*Assumptions!B6 -> 16814925 | C8: =B8*(1-Assumptions!B32)-Assumptions!B19*Assumptions!B33 -> 15752956 | D8: =-Assumptions!B15 -> -16252413 | E8: =C8+D8 -> -499456.74
A9: 80 | B9: =A9*Assumptions!B6 -> 17935920 | C9: =B9*(1-Assumptions!B32)-Assumptions!B19*Assumptions!B33 -> 16851531 | D9: =-Assumptions!B15 -> -16252413 | E9: =C9+D9 -> 599118.36
A10: 85 | B10: =A10*Assumptions!B6 -> 19056915 | C10: =B10*(1-Assumptions!B32)-Assumptions!B19*Assumptions!B33 -> 17950106 | D10: =-Assumptions!B15 -> -16252413 | E10: =C10+D10 -> 1697693.5
A11: 90 | B11: =A11*Assumptions!B6 -> 20177910 | C11: =B11*(1-Assumptions!B32)-Assumptions!B19*Assumptions!B33 -> 19048682 | D11: =-Assumptions!B15 -> -16252413 | E11: =C11+D11 -> 2796268.6
A12: 95 | B12: =A12*Assumptions!B6 -> 21298905 | C12: =B12*(1-Assumptions!B32)-Assumptions!B19*Assumptions!B33 -> 20147257 | D12: =-Assumptions!B15 -> -16252413 | E12: =C12+D12 -> 3894843.7
A13: 100 | B13: =A13*Assumptions!B6 -> 22419900 | C13: =B13*(1-Assumptions!B32)-Assumptions!B19*Assumptions!B33 -> 21245832 | D13: =-Assumptions!B15 -> -16252413 | E13: =C13+D13 -> 4993418.8
A14: 110 | B14: =A14*Assumptions!B6 -> 24661890 | C14: =B14*(1-Assumptions!B32)-Assumptions!B19*Assumptions!B33 -> 23442982 | D14: =-Assumptions!B15 -> -16252413 | E14: =C14+D14 -> 7190569
A15: 116 | B15: =A15*Assumptions!B6 -> 26007084 | C15: =B15*(1-Assumptions!B32)-Assumptions!B19*Assumptions!B33 -> 24761272 | D15: =-Assumptions!B15 -> -16252413 | E15: =C15+D15 -> 8508859.1
A16: 120 | B16: =A16*Assumptions!B6 -> 26903880 | C16: =B16*(1-Assumptions!B32)-Assumptions!B19*Assumptions!B33 -> 25640132 | D16: =-Assumptions!B15 -> -16252413 | E16: =C16+D16 -> 9387719.2
A17: 130 | B17: =A17*Assumptions!B6 -> 29145870 | C17: =B17*(1-Assumptions!B32)-Assumptions!B19*Assumptions!B33 -> 27837282 | D17: =-Assumptions!B15 -> -16252413 | E17: =C17+D17 -> 11584869
A18: 140 | B18: =A18*Assumptions!B6 -> 31387860 | C18: =B18*(1-Assumptions!B32)-Assumptions!B19*Assumptions!B33 -> 30034433 | D18: =-Assumptions!B15 -> -16252413 | E18: =C18+D18 -> 13782020
A19: 150 | B19: =A19*Assumptions!B6 -> 33629850 | C19: =B19*(1-Assumptions!B32)-Assumptions!B19*Assumptions!B33 -> 32231583 | D19: =-Assumptions!B15 -> -16252413 | E19: =C19+D19 -> 15979170
A21: Breakeven $/SF (approx) | B21: =Assumptions!B15/(Assumptions!B6*(1-Assumptions!B32))+Assumptions!B19*Assumptions!B33/(Assumptions!B6*(1-Assumptions!B32)) -> 77.273203

Sheet Comparable Sales Evidence
A1: Comparable Sales Evidence — Distressed / Value-Add Suburban Office
A3: Property | B3: $/SF | C3: Sale Year | D3: Total SF | E3: Yr Built | F3: Acres | G3: Notes
A4: 400 Deaderick St | B4: 54 | C4: 2025 | D4: 295914 | E4: 1985 | F4: 0.57 | G4: Downtown distressed — floor comp
A5: 100 Centerview Dr | B5: 78 | C5: 2025 | D5: 248573 | E5: 1984 | F5: 25.36 | G5: Suburban, similar size, OL zoning
A6: 41 Rachel Dr | B6: 70 | C6: 2025 | D6: 157262 | E6: 1992 | F6: 13.5 | G6: Suburban distressed
A7: 3343 Perimeter Hill Dr | B7: 72 | C7: 2018 | D7: 73352 | E7: 1985 | F7: 3.58 | G7: Same vintage, suburban value-add
A8: 424 Church St (resale) | B8: 85 | C8: 2025 | D8: 647732 | E8: 1985 | F8: 0.83 | G8: CBD distressed resale
A9: 1 Burton Hills Blvd | B9: 98 | C9: 2025 | D9: 121968 | E9: 1985 | F9: 7.07 | G9: Same vintage, suburban
A10: 1321 Murfreesboro Pike | B10: 97 | C10: 2021 | D10: 189836 | E10: 1987 | F10: 5.3 | G10: South Nashville corridor
A11: 215 Cumberland Bnd | B11: 107 | C11: 2020 | D11: 101124 | E11: 1980 | F11: 8.2 | G11: IWD zoning, same era
A12: 636 Grassmere Park | B12: 236 | C12: 2022 | D12: 63474 | E12: 1985 | F12: 6.02 | G12: Same park — but OCCUPIED (ceiling)
A13: 200 Athens Way | B13: 146 | C13: 2019 | D13: 246151 | E13: 1985 | F13: 8.7 | G13: IWD, same vintage — OCCUPIED
A15: Distressed Comp Avg ($/SF) | B15: =AVERAGE(B4:B10) -> 79.142857
A16: All Comp Avg ($/SF) | B16: =AVERAGE(B4:B13) -> 104.3
A18: PRICING RATIONALE
A19: Low Case ($65/SF): Below distressed comp average. Assumes forced sale, no buyer competition.
A20: Base Case ($85/SF): Aligns with 424 Church resale and 100 Centerview. Reflects 73% vacancy discount.
A21: High Case ($115/SF): Near 2015 acquisition basis. Requires competitive bidding from IWD/warehouse buyer.
